layab/__init__.py
layab/_configuration.py
layab/flask_restx.py
layab/starlette.py
layab/version.py
layab-2.2.0.dist-info/LICENSE
layab-2.2.0.dist-info/METADATA
layab-2.2.0.dist-info/WHEEL
layab-2.2.0.dist-info/top_level.txt
layab-2.2.0.dist-info/RECORD
