Metadata-Version: 2.1
Name: layab
Version: 2.2.0
Summary: Wonderful REST APIs.
Home-page: https://colin-b.github.io/layab/
Author: Colin Bounouar
Author-email: colin.bounouar.dev@gmail.com
Maintainer: Colin Bounouar
Maintainer-email: colin.bounouar.dev@gmail.com
License: MIT
Download-URL: https://pypi.org/project/layab/
Project-URL: GitHub, https://github.com/Colin-b/layab
Project-URL: Changelog, https://github.com/Colin-b/layab/blob/master/CHANGELOG.md
Project-URL: Issues, https://github.com/Colin-b/layab/issues
Keywords: api,starlette,flask,flask-restx,configuration,proxyfix
Platform: Windows
Platform: Linux
Classifier: Development Status :: 5 - Production/Stable
Classifier: Intended Audience :: Developers
Classifier: License :: OSI Approved :: MIT License
Classifier: Natural Language :: English
Classifier: Programming Language :: Python
Classifier: Programming Language :: Python :: 3
Classifier: Programming Language :: Python :: 3.6
Classifier: Programming Language :: Python :: 3.7
Classifier: Programming Language :: Python :: 3.8
Classifier: Programming Language :: Python :: 3.9
Classifier: Topic :: Software Development :: Build Tools
Requires-Python: >=3.6
Requires-Dist: PyYAML (==5.*)
Provides-Extra: testing
Requires-Dist: starlette (==0.13.*) ; extra == 'testing'
Requires-Dist: requests (==2.*) ; extra == 'testing'
Requires-Dist: flask-restx (==0.2.*) ; extra == 'testing'
Requires-Dist: flask-cors (==3.*) ; extra == 'testing'
Requires-Dist: flask-compress (==1.*) ; extra == 'testing'
Requires-Dist: pytest-cov (==2.*) ; extra == 'testing'
